zhouyuqin/__init__.py
zhouyuqin/main.py
zhouyuqin-0.1.1.dist-info/METADATA
zhouyuqin-0.1.1.dist-info/WHEEL
zhouyuqin-0.1.1.dist-info/top_level.txt
zhouyuqin-0.1.1.dist-info/RECORD
